WxL/WxCore.py
WxL/WxWidgets.py
WxL/__init__.py
WxLand-0.0.5.dist-info/LICENSE
WxLand-0.0.5.dist-info/METADATA
WxLand-0.0.5.dist-info/WHEEL
WxLand-0.0.5.dist-info/entry_points.txt
WxLand-0.0.5.dist-info/top_level.txt
WxLand-0.0.5.dist-info/RECORD
